batt_utility/__init__.py
batt_utility/data_models.py
batt_utility/helper_functions.py
batt_utility-0.1.3.dist-info/licenses/LICENSE.txt
batt_utility-0.1.3.dist-info/METADATA
batt_utility-0.1.3.dist-info/WHEEL
batt_utility-0.1.3.dist-info/top_level.txt
batt_utility-0.1.3.dist-info/RECORD
