Metadata-Version: 2.4
Name: batt-utility
Version: 0.1.3
Summary: Utility functions for OpenBattTools
Home-page: https://github.com/OpenBattTools/batt-utility
Author: Lukas Gold
Author-email: lukas.gold@isc.fraunhofer.de
License: AGPL-3.0-or-later
Project-URL: Documentation, https://github.com/OpenBattTools/batt-utility
Platform: any
Classifier: Development Status :: 3 - Alpha
Classifier: Programming Language :: Python
Requires-Python: >=3.8
License-File: LICENSE.txt
Requires-Dist: pandas
Requires-Dist: pathlib
Requires-Dist: pydantic
Requires-Dist: sphinx
Requires-Dist: strenum; python_version < "3.11"
Requires-Dist: typing_extensions
Provides-Extra: testing
Requires-Dist: setuptools; extra == "testing"
Requires-Dist: pytest; extra == "testing"
Requires-Dist: pytest-cov; extra == "testing"
Dynamic: license-file
